[{"pk": 1, "model": "campus.trashbin", "fields": {"token": "11B1GER", "current_amount": 0, "total_amount": 10, "location_x": 1, "location_y": 0, "floor": 1, "created_at": "2022-07-28 11:04:05.684196", "updated_at": "2022-07-28 11:04:05.684196"}}, {"pk": 2, "model": "campus.trashbin", "fields": {"token": "11B1PET", "current_amount": 0, "total_amount": 10, "location_x": 2, "location_y": 0, "floor": 1, "created_at": "2022-07-28 11:04:05.684196", "updated_at": "2022-07-28 11:04:05.684196"}}, {"pk": 3, "model": "campus.trashbin", "fields": {"token": "11B1CAN", "current_amount": 0, "total_amount": 10, "location_x": 3, "location_y": 0, "floor": 1, "created_at": "2022-07-28 11:04:05.684196", "updated_at": "2022-07-28 11:04:05.684196"}}, {"pk": 4, "model": "campus.trashbin", "fields": {"token": "11B1GLA", "current_amount": 0, "total_amount": 10, "location_x": 4, "location_y": 0, "floor": 1, "created_at": "2022-07-28 11:04:05.684196", "updated_at": "2022-07-28 11:04:05.684196"}}, {"pk": 5, "model": "campus.trashbin", "fields": {"token": "11B1PPR", "current_amount": 0, "total_amount": 10, "location_x": 5, "location_y": 0, "floor": 1, "created_at": "2022-07-28 11:04:05.684196", "updated_at": "2022-07-28 11:04:05.684196"}}, {"pk": 6, "model": "campus.trashbin", "fields": {"token": "11B2GER", "current_amount": 0, "total_amount": 10, "location_x": 1, "location_y": 0, "floor": 2, "created_at": "2022-07-28 11:04:05.684196", "updated_at": "2022-07-28 11:04:05.684196"}}, {"pk": 7, "model": "campus.trashbin", "fields": {"token": "11B2PET", "current_amount": 0, "total_amount": 10, "location_x": 2, "location_y": 0, "floor": 2, "created_at": "2022-07-28 11:04:05.684196", "updated_at": "2022-07-28 11:04:05.684196"}}, {"pk": 8, "model": "campus.trashbin", "fields": {"token": "11B2CAN", "current_amount": 0, "total_amount": 10, "location_x": 3, "location_y": 0, "floor": 2, "created_at": "2022-07-28 11:04:05.684196", "updated_at": "2022-07-28 11:04:05.684196"}}, {"pk": 9, "model": "campus.trashbin", "fields": {"token": "11B2GLA", "current_amount": 0, "total_amount": 10, "location_x": 4, "location_y": 0, "floor": 2, "created_at": "2022-07-28 11:04:05.684196", "updated_at": "2022-07-28 11:04:05.684196"}}, {"pk": 10, "model": "campus.trashbin", "fields": {"token": "11B2PPR", "current_amount": 0, "total_amount": 10, "location_x": 5, "location_y": 0, "floor": 2, "created_at": "2022-07-28 11:04:05.684196", "updated_at": "2022-07-28 11:04:05.684196"}}, {"pk": 11, "model": "campus.trashbin", "fields": {"token": "111GER", "current_amount": 0, "total_amount": 10, "location_x": 1, "location_y": 0, "floor": 3, "created_at": "2022-07-28 11:04:05.684196", "updated_at": "2022-07-28 11:04:05.684196"}}, {"pk": 12, "model": "campus.trashbin", "fields": {"token": "111PET", "current_amount": 0, "total_amount": 10, "location_x": 2, "location_y": 0, "floor": 3, "created_at": "2022-07-28 11:04:05.684196", "updated_at": "2022-07-28 11:04:05.684196"}}, {"pk": 13, "model": "campus.trashbin", "fields": {"token": "111CAN", "current_amount": 0, "total_amount": 10, "location_x": 3, "location_y": 0, "floor": 3, "created_at": "2022-07-28 11:04:05.684196", "updated_at": "2022-07-28 11:04:05.684196"}}, {"pk": 14, "model": "campus.trashbin", "fields": {"token": "111GLA", "current_amount": 0, "total_amount": 10, "location_x": 4, "location_y": 0, "floor": 3, "created_at": "2022-07-28 11:04:05.684196", "updated_at": "2022-07-28 11:04:05.684196"}}, {"pk": 15, "model": "campus.trashbin", "fields": {"token": "111PPR", "current_amount": 0, "total_amount": 10, "location_x": 5, "location_y": 0, "floor": 3, "created_at": "2022-07-28 11:04:05.684196", "updated_at": "2022-07-28 11:04:05.684196"}}, {"pk": 16, "model": "campus.trashbin", "fields": {"token": "112GER", "current_amount": 0, "total_amount": 10, "location_x": 1, "location_y": 0, "floor": 4, "created_at": "2022-07-28 11:04:05.684196", "updated_at": "2022-07-28 11:04:05.684196"}}, {"pk": 17, "model": "campus.trashbin", "fields": {"token": "112PET", "current_amount": 0, "total_amount": 10, "location_x": 2, "location_y": 0, "floor": 4, "created_at": "2022-07-28 11:04:05.684196", "updated_at": "2022-07-28 11:04:05.684196"}}, {"pk": 18, "model": "campus.trashbin", "fields": {"token": "112CAN", "current_amount": 0, "total_amount": 10, "location_x": 3, "location_y": 0, "floor": 4, "created_at": "2022-07-28 11:04:05.684196", "updated_at": "2022-07-28 11:04:05.684196"}}, {"pk": 19, "model": "campus.trashbin", "fields": {"token": "112GLA", "current_amount": 0, "total_amount": 10, "location_x": 4, "location_y": 0, "floor": 4, "created_at": "2022-07-28 11:04:05.684196", "updated_at": "2022-07-28 11:04:05.684196"}}, {"pk": 20, "model": "campus.trashbin", "fields": {"token": "112PPR", "current_amount": 0, "total_amount": 10, "location_x": 5, "location_y": 0, "floor": 4, "created_at": "2022-07-28 11:04:05.684196", "updated_at": "2022-07-28 11:04:05.684196"}}, {"pk": 21, "model": "campus.trashbin", "fields": {"token": "113GER", "current_amount": 0, "total_amount": 10, "location_x": 1, "location_y": 0, "floor": 5, "created_at": "2022-07-28 11:04:05.684196", "updated_at": "2022-07-28 11:04:05.684196"}}, {"pk": 22, "model": "campus.trashbin", "fields": {"token": "113PET", "current_amount": 0, "total_amount": 10, "location_x": 2, "location_y": 0, "floor": 5, "created_at": "2022-07-28 11:04:05.684196", "updated_at": "2022-07-28 11:04:05.684196"}}, {"pk": 23, "model": "campus.trashbin", "fields": {"token": "113CAN", "current_amount": 0, "total_amount": 10, "location_x": 3, "location_y": 0, "floor": 5, "created_at": "2022-07-28 11:04:05.684196", "updated_at": "2022-07-28 11:04:05.684196"}}, {"pk": 24, "model": "campus.trashbin", "fields": {"token": "113GLA", "current_amount": 0, "total_amount": 10, "location_x": 4, "location_y": 0, "floor": 5, "created_at": "2022-07-28 11:04:05.684196", "updated_at": "2022-07-28 11:04:05.684196"}}, {"pk": 25, "model": "campus.trashbin", "fields": {"token": "113PPR", "current_amount": 0, "total_amount": 10, "location_x": 5, "location_y": 0, "floor": 5, "created_at": "2022-07-28 11:04:05.684196", "updated_at": "2022-07-28 11:04:05.684196"}}, {"pk": 26, "model": "campus.trashbin", "fields": {"token": "114GER", "current_amount": 0, "total_amount": 10, "location_x": 1, "location_y": 0, "floor": 6, "created_at": "2022-07-28 11:04:05.684196", "updated_at": "2022-07-28 11:04:05.684196"}}, {"pk": 27, "model": "campus.trashbin", "fields": {"token": "114PET", "current_amount": 0, "total_amount": 10, "location_x": 2, "location_y": 0, "floor": 6, "created_at": "2022-07-28 11:04:05.684196", "updated_at": "2022-07-28 11:04:05.684196"}}, {"pk": 28, "model": "campus.trashbin", "fields": {"token": "114CAN", "current_amount": 0, "total_amount": 10, "location_x": 3, "location_y": 0, "floor": 6, "created_at": "2022-07-28 11:04:05.684196", "updated_at": "2022-07-28 11:04:05.684196"}}, {"pk": 29, "model": "campus.trashbin", "fields": {"token": "114GLA", "current_amount": 0, "total_amount": 10, "location_x": 4, "location_y": 0, "floor": 6, "created_at": "2022-07-28 11:04:05.684196", "updated_at": "2022-07-28 11:04:05.684196"}}, {"pk": 30, "model": "campus.trashbin", "fields": {"token": "114PPR", "current_amount": 0, "total_amount": 10, "location_x": 5, "location_y": 0, "floor": 6, "created_at": "2022-07-28 11:04:05.684196", "updated_at": "2022-07-28 11:04:05.684196"}}, {"pk": 31, "model": "campus.trashbin", "fields": {"token": "12B1GER", "current_amount": 0, "total_amount": 10, "location_x": 1, "location_y": 0, "floor": 7, "created_at": "2022-07-28 11:04:05.684196", "updated_at": "2022-07-28 11:04:05.684196"}}, {"pk": 32, "model": "campus.trashbin", "fields": {"token": "12B1PET", "current_amount": 0, "total_amount": 10, "location_x": 2, "location_y": 0, "floor": 7, "created_at": "2022-07-28 11:04:05.684196", "updated_at": "2022-07-28 11:04:05.684196"}}, {"pk": 33, "model": "campus.trashbin", "fields": {"token": "12B1CAN", "current_amount": 0, "total_amount": 10, "location_x": 3, "location_y": 0, "floor": 7, "created_at": "2022-07-28 11:04:05.684196", "updated_at": "2022-07-28 11:04:05.684196"}}, {"pk": 34, "model": "campus.trashbin", "fields": {"token": "12B1GLA", "current_amount": 0, "total_amount": 10, "location_x": 4, "location_y": 0, "floor": 7, "created_at": "2022-07-28 11:04:05.684196", "updated_at": "2022-07-28 11:04:05.684196"}}, {"pk": 35, "model": "campus.trashbin", "fields": {"token": "12B1PPR", "current_amount": 0, "total_amount": 10, "location_x": 5, "location_y": 0, "floor": 7, "created_at": "2022-07-28 11:04:05.684196", "updated_at": "2022-07-28 11:04:05.684196"}}, {"pk": 36, "model": "campus.trashbin", "fields": {"token": "12B2GER", "current_amount": 0, "total_amount": 10, "location_x": 1, "location_y": 0, "floor": 8, "created_at": "2022-07-28 11:04:05.684196", "updated_at": "2022-07-28 11:04:05.684196"}}, {"pk": 37, "model": "campus.trashbin", "fields": {"token": "12B2PET", "current_amount": 0, "total_amount": 10, "location_x": 2, "location_y": 0, "floor": 8, "created_at": "2022-07-28 11:04:05.684196", "updated_at": "2022-07-28 11:04:05.684196"}}, {"pk": 38, "model": "campus.trashbin", "fields": {"token": "12B2CAN", "current_amount": 0, "total_amount": 10, "location_x": 3, "location_y": 0, "floor": 8, "created_at": "2022-07-28 11:04:05.684196", "updated_at": "2022-07-28 11:04:05.684196"}}, {"pk": 39, "model": "campus.trashbin", "fields": {"token": "12B2GLA", "current_amount": 0, "total_amount": 10, "location_x": 4, "location_y": 0, "floor": 8, "created_at": "2022-07-28 11:04:05.684196", "updated_at": "2022-07-28 11:04:05.684196"}}, {"pk": 40, "model": "campus.trashbin", "fields": {"token": "12B2PPR", "current_amount": 0, "total_amount": 10, "location_x": 5, "location_y": 0, "floor": 8, "created_at": "2022-07-28 11:04:05.684196", "updated_at": "2022-07-28 11:04:05.684196"}}, {"pk": 41, "model": "campus.trashbin", "fields": {"token": "121GER", "current_amount": 0, "total_amount": 10, "location_x": 1, "location_y": 0, "floor": 9, "created_at": "2022-07-28 11:04:05.684196", "updated_at": "2022-07-28 11:04:05.684196"}}, {"pk": 42, "model": "campus.trashbin", "fields": {"token": "121PET", "current_amount": 0, "total_amount": 10, "location_x": 2, "location_y": 0, "floor": 9, "created_at": "2022-07-28 11:04:05.684196", "updated_at": "2022-07-28 11:04:05.684196"}}, {"pk": 43, "model": "campus.trashbin", "fields": {"token": "121CAN", "current_amount": 0, "total_amount": 10, "location_x": 3, "location_y": 0, "floor": 9, "created_at": "2022-07-28 11:04:05.684196", "updated_at": "2022-07-28 11:04:05.684196"}}, {"pk": 44, "model": "campus.trashbin", "fields": {"token": "121GLA", "current_amount": 0, "total_amount": 10, "location_x": 4, "location_y": 0, "floor": 9, "created_at": "2022-07-28 11:04:05.684196", "updated_at": "2022-07-28 11:04:05.684196"}}, {"pk": 45, "model": "campus.trashbin", "fields": {"token": "121PPR", "current_amount": 0, "total_amount": 10, "location_x": 5, "location_y": 0, "floor": 9, "created_at": "2022-07-28 11:04:05.684196", "updated_at": "2022-07-28 11:04:05.684196"}}, {"pk": 46, "model": "campus.trashbin", "fields": {"token": "122GER", "current_amount": 0, "total_amount": 10, "location_x": 1, "location_y": 0, "floor": 10, "created_at": "2022-07-28 11:04:05.684196", "updated_at": "2022-07-28 11:04:05.684196"}}, {"pk": 47, "model": "campus.trashbin", "fields": {"token": "122PET", "current_amount": 0, "total_amount": 10, "location_x": 2, "location_y": 0, "floor": 10, "created_at": "2022-07-28 11:04:05.684196", "updated_at": "2022-07-28 11:04:05.684196"}}, {"pk": 48, "model": "campus.trashbin", "fields": {"token": "122CAN", "current_amount": 0, "total_amount": 10, "location_x": 3, "location_y": 0, "floor": 10, "created_at": "2022-07-28 11:04:05.684196", "updated_at": "2022-07-28 11:04:05.684196"}}, {"pk": 49, "model": "campus.trashbin", "fields": {"token": "122GLA", "current_amount": 0, "total_amount": 10, "location_x": 4, "location_y": 0, "floor": 10, "created_at": "2022-07-28 11:04:05.684196", "updated_at": "2022-07-28 11:04:05.684196"}}, {"pk": 50, "model": "campus.trashbin", "fields": {"token": "122PPR", "current_amount": 0, "total_amount": 10, "location_x": 5, "location_y": 0, "floor": 10, "created_at": "2022-07-28 11:04:05.684196", "updated_at": "2022-07-28 11:04:05.684196"}}, {"pk": 51, "model": "campus.trashbin", "fields": {"token": "123GER", "current_amount": 0, "total_amount": 10, "location_x": 1, "location_y": 0, "floor": 11, "created_at": "2022-07-28 11:04:05.684196", "updated_at": "2022-07-28 11:04:05.684196"}}, {"pk": 52, "model": "campus.trashbin", "fields": {"token": "123PET", "current_amount": 0, "total_amount": 10, "location_x": 2, "location_y": 0, "floor": 11, "created_at": "2022-07-28 11:04:05.684196", "updated_at": "2022-07-28 11:04:05.684196"}}, {"pk": 53, "model": "campus.trashbin", "fields": {"token": "123CAN", "current_amount": 0, "total_amount": 10, "location_x": 3, "location_y": 0, "floor": 11, "created_at": "2022-07-28 11:04:05.684196", "updated_at": "2022-07-28 11:04:05.684196"}}, {"pk": 54, "model": "campus.trashbin", "fields": {"token": "123GLA", "current_amount": 0, "total_amount": 10, "location_x": 4, "location_y": 0, "floor": 11, "created_at": "2022-07-28 11:04:05.684196", "updated_at": "2022-07-28 11:04:05.684196"}}, {"pk": 55, "model": "campus.trashbin", "fields": {"token": "123PPR", "current_amount": 0, "total_amount": 10, "location_x": 5, "location_y": 0, "floor": 11, "created_at": "2022-07-28 11:04:05.684196", "updated_at": "2022-07-28 11:04:05.684196"}}, {"pk": 56, "model": "campus.trashbin", "fields": {"token": "124GER", "current_amount": 0, "total_amount": 10, "location_x": 1, "location_y": 0, "floor": 12, "created_at": "2022-07-28 11:04:05.684196", "updated_at": "2022-07-28 11:04:05.684196"}}, {"pk": 57, "model": "campus.trashbin", "fields": {"token": "124PET", "current_amount": 0, "total_amount": 10, "location_x": 2, "location_y": 0, "floor": 12, "created_at": "2022-07-28 11:04:05.684196", "updated_at": "2022-07-28 11:04:05.684196"}}, {"pk": 58, "model": "campus.trashbin", "fields": {"token": "124CAN", "current_amount": 0, "total_amount": 10, "location_x": 3, "location_y": 0, "floor": 12, "created_at": "2022-07-28 11:04:05.684196", "updated_at": "2022-07-28 11:04:05.684196"}}, {"pk": 59, "model": "campus.trashbin", "fields": {"token": "124GLA", "current_amount": 0, "total_amount": 10, "location_x": 4, "location_y": 0, "floor": 12, "created_at": "2022-07-28 11:04:05.684196", "updated_at": "2022-07-28 11:04:05.684196"}}, {"pk": 60, "model": "campus.trashbin", "fields": {"token": "124PPR", "current_amount": 0, "total_amount": 10, "location_x": 5, "location_y": 0, "floor": 12, "created_at": "2022-07-28 11:04:05.684196", "updated_at": "2022-07-28 11:04:05.684196"}}, {"pk": 61, "model": "campus.trashbin", "fields": {"token": "13B1GER", "current_amount": 0, "total_amount": 10, "location_x": 1, "location_y": 0, "floor": 13, "created_at": "2022-07-28 11:04:05.684196", "updated_at": "2022-07-28 11:04:05.684196"}}, {"pk": 62, "model": "campus.trashbin", "fields": {"token": "13B1PET", "current_amount": 0, "total_amount": 10, "location_x": 2, "location_y": 0, "floor": 13, "created_at": "2022-07-28 11:04:05.684196", "updated_at": "2022-07-28 11:04:05.684196"}}, {"pk": 63, "model": "campus.trashbin", "fields": {"token": "13B1CAN", "current_amount": 0, "total_amount": 10, "location_x": 3, "location_y": 0, "floor": 13, "created_at": "2022-07-28 11:04:05.684196", "updated_at": "2022-07-28 11:04:05.684196"}}, {"pk": 64, "model": "campus.trashbin", "fields": {"token": "13B1GLA", "current_amount": 0, "total_amount": 10, "location_x": 4, "location_y": 0, "floor": 13, "created_at": "2022-07-28 11:04:05.684196", "updated_at": "2022-07-28 11:04:05.684196"}}, {"pk": 65, "model": "campus.trashbin", "fields": {"token": "13B1PPR", "current_amount": 0, "total_amount": 10, "location_x": 5, "location_y": 0, "floor": 13, "created_at": "2022-07-28 11:04:05.684196", "updated_at": "2022-07-28 11:04:05.684196"}}, {"pk": 66, "model": "campus.trashbin", "fields": {"token": "13B2GER", "current_amount": 0, "total_amount": 10, "location_x": 1, "location_y": 0, "floor": 14, "created_at": "2022-07-28 11:04:05.684196", "updated_at": "2022-07-28 11:04:05.684196"}}, {"pk": 67, "model": "campus.trashbin", "fields": {"token": "13B2PET", "current_amount": 0, "total_amount": 10, "location_x": 2, "location_y": 0, "floor": 14, "created_at": "2022-07-28 11:04:05.684196", "updated_at": "2022-07-28 11:04:05.684196"}}, {"pk": 68, "model": "campus.trashbin", "fields": {"token": "13B2CAN", "current_amount": 0, "total_amount": 10, "location_x": 3, "location_y": 0, "floor": 14, "created_at": "2022-07-28 11:04:05.684196", "updated_at": "2022-07-28 11:04:05.684196"}}, {"pk": 69, "model": "campus.trashbin", "fields": {"token": "13B2GLA", "current_amount": 0, "total_amount": 10, "location_x": 4, "location_y": 0, "floor": 14, "created_at": "2022-07-28 11:04:05.684196", "updated_at": "2022-07-28 11:04:05.684196"}}, {"pk": 70, "model": "campus.trashbin", "fields": {"token": "13B2PPR", "current_amount": 0, "total_amount": 10, "location_x": 5, "location_y": 0, "floor": 14, "created_at": "2022-07-28 11:04:05.684196", "updated_at": "2022-07-28 11:04:05.684196"}}, {"pk": 71, "model": "campus.trashbin", "fields": {"token": "131GER", "current_amount": 0, "total_amount": 10, "location_x": 1, "location_y": 0, "floor": 15, "created_at": "2022-07-28 11:04:05.684196", "updated_at": "2022-07-28 11:04:05.684196"}}, {"pk": 72, "model": "campus.trashbin", "fields": {"token": "131PET", "current_amount": 0, "total_amount": 10, "location_x": 2, "location_y": 0, "floor": 15, "created_at": "2022-07-28 11:04:05.684196", "updated_at": "2022-07-28 11:04:05.684196"}}, {"pk": 73, "model": "campus.trashbin", "fields": {"token": "131CAN", "current_amount": 0, "total_amount": 10, "location_x": 3, "location_y": 0, "floor": 15, "created_at": "2022-07-28 11:04:05.684196", "updated_at": "2022-07-28 11:04:05.684196"}}, {"pk": 74, "model": "campus.trashbin", "fields": {"token": "131GLA", "current_amount": 0, "total_amount": 10, "location_x": 4, "location_y": 0, "floor": 15, "created_at": "2022-07-28 11:04:05.684196", "updated_at": "2022-07-28 11:04:05.684196"}}, {"pk": 75, "model": "campus.trashbin", "fields": {"token": "131PPR", "current_amount": 0, "total_amount": 10, "location_x": 5, "location_y": 0, "floor": 15, "created_at": "2022-07-28 11:04:05.684196", "updated_at": "2022-07-28 11:04:05.684196"}}, {"pk": 76, "model": "campus.trashbin", "fields": {"token": "132GER", "current_amount": 0, "total_amount": 10, "location_x": 1, "location_y": 0, "floor": 16, "created_at": "2022-07-28 11:04:05.684196", "updated_at": "2022-07-28 11:04:05.684196"}}, {"pk": 77, "model": "campus.trashbin", "fields": {"token": "132PET", "current_amount": 0, "total_amount": 10, "location_x": 2, "location_y": 0, "floor": 16, "created_at": "2022-07-28 11:04:05.684196", "updated_at": "2022-07-28 11:04:05.684196"}}, {"pk": 78, "model": "campus.trashbin", "fields": {"token": "132CAN", "current_amount": 0, "total_amount": 10, "location_x": 3, "location_y": 0, "floor": 16, "created_at": "2022-07-28 11:04:05.684196", "updated_at": "2022-07-28 11:04:05.684196"}}, {"pk": 79, "model": "campus.trashbin", "fields": {"token": "132GLA", "current_amount": 0, "total_amount": 10, "location_x": 4, "location_y": 0, "floor": 16, "created_at": "2022-07-28 11:04:05.684196", "updated_at": "2022-07-28 11:04:05.684196"}}, {"pk": 80, "model": "campus.trashbin", "fields": {"token": "132PPR", "current_amount": 0, "total_amount": 10, "location_x": 5, "location_y": 0, "floor": 16, "created_at": "2022-07-28 11:04:05.684196", "updated_at": "2022-07-28 11:04:05.684196"}}, {"pk": 81, "model": "campus.trashbin", "fields": {"token": "133GER", "current_amount": 0, "total_amount": 10, "location_x": 1, "location_y": 0, "floor": 17, "created_at": "2022-07-28 11:04:05.684196", "updated_at": "2022-07-28 11:04:05.684196"}}, {"pk": 82, "model": "campus.trashbin", "fields": {"token": "133PET", "current_amount": 0, "total_amount": 10, "location_x": 2, "location_y": 0, "floor": 17, "created_at": "2022-07-28 11:04:05.684196", "updated_at": "2022-07-28 11:04:05.684196"}}, {"pk": 83, "model": "campus.trashbin", "fields": {"token": "133CAN", "current_amount": 0, "total_amount": 10, "location_x": 3, "location_y": 0, "floor": 17, "created_at": "2022-07-28 11:04:05.684196", "updated_at": "2022-07-28 11:04:05.684196"}}, {"pk": 84, "model": "campus.trashbin", "fields": {"token": "133GLA", "current_amount": 0, "total_amount": 10, "location_x": 4, "location_y": 0, "floor": 17, "created_at": "2022-07-28 11:04:05.684196", "updated_at": "2022-07-28 11:04:05.684196"}}, {"pk": 85, "model": "campus.trashbin", "fields": {"token": "133PPR", "current_amount": 0, "total_amount": 10, "location_x": 5, "location_y": 0, "floor": 17, "created_at": "2022-07-28 11:04:05.684196", "updated_at": "2022-07-28 11:04:05.684196"}}, {"pk": 86, "model": "campus.trashbin", "fields": {"token": "134GER", "current_amount": 0, "total_amount": 10, "location_x": 1, "location_y": 0, "floor": 18, "created_at": "2022-07-28 11:04:05.684196", "updated_at": "2022-07-28 11:04:05.684196"}}, {"pk": 87, "model": "campus.trashbin", "fields": {"token": "134PET", "current_amount": 0, "total_amount": 10, "location_x": 2, "location_y": 0, "floor": 18, "created_at": "2022-07-28 11:04:05.684196", "updated_at": "2022-07-28 11:04:05.684196"}}, {"pk": 88, "model": "campus.trashbin", "fields": {"token": "134CAN", "current_amount": 0, "total_amount": 10, "location_x": 3, "location_y": 0, "floor": 18, "created_at": "2022-07-28 11:04:05.684196", "updated_at": "2022-07-28 11:04:05.684196"}}, {"pk": 89, "model": "campus.trashbin", "fields": {"token": "134GLA", "current_amount": 0, "total_amount": 10, "location_x": 4, "location_y": 0, "floor": 18, "created_at": "2022-07-28 11:04:05.684196", "updated_at": "2022-07-28 11:04:05.684196"}}, {"pk": 90, "model": "campus.trashbin", "fields": {"token": "134PPR", "current_amount": 0, "total_amount": 10, "location_x": 5, "location_y": 0, "floor": 18, "created_at": "2022-07-28 11:04:05.684196", "updated_at": "2022-07-28 11:04:05.684196"}}, {"pk": 91, "model": "campus.trashbin", "fields": {"token": "14B1GER", "current_amount": 0, "total_amount": 10, "location_x": 1, "location_y": 0, "floor": 19, "created_at": "2022-07-28 11:04:05.684196", "updated_at": "2022-07-28 11:04:05.684196"}}, {"pk": 92, "model": "campus.trashbin", "fields": {"token": "14B1PET", "current_amount": 0, "total_amount": 10, "location_x": 2, "location_y": 0, "floor": 19, "created_at": "2022-07-28 11:04:05.684196", "updated_at": "2022-07-28 11:04:05.684196"}}, {"pk": 93, "model": "campus.trashbin", "fields": {"token": "14B1CAN", "current_amount": 0, "total_amount": 10, "location_x": 3, "location_y": 0, "floor": 19, "created_at": "2022-07-28 11:04:05.684196", "updated_at": "2022-07-28 11:04:05.684196"}}, {"pk": 94, "model": "campus.trashbin", "fields": {"token": "14B1GLA", "current_amount": 0, "total_amount": 10, "location_x": 4, "location_y": 0, "floor": 19, "created_at": "2022-07-28 11:04:05.684196", "updated_at": "2022-07-28 11:04:05.684196"}}, {"pk": 95, "model": "campus.trashbin", "fields": {"token": "14B1PPR", "current_amount": 0, "total_amount": 10, "location_x": 5, "location_y": 0, "floor": 19, "created_at": "2022-07-28 11:04:05.684196", "updated_at": "2022-07-28 11:04:05.684196"}}, {"pk": 96, "model": "campus.trashbin", "fields": {"token": "14B2GER", "current_amount": 0, "total_amount": 10, "location_x": 1, "location_y": 0, "floor": 20, "created_at": "2022-07-28 11:04:05.684196", "updated_at": "2022-07-28 11:04:05.684196"}}, {"pk": 97, "model": "campus.trashbin", "fields": {"token": "14B2PET", "current_amount": 0, "total_amount": 10, "location_x": 2, "location_y": 0, "floor": 20, "created_at": "2022-07-28 11:04:05.684196", "updated_at": "2022-07-28 11:04:05.684196"}}, {"pk": 98, "model": "campus.trashbin", "fields": {"token": "14B2CAN", "current_amount": 0, "total_amount": 10, "location_x": 3, "location_y": 0, "floor": 20, "created_at": "2022-07-28 11:04:05.684196", "updated_at": "2022-07-28 11:04:05.684196"}}, {"pk": 99, "model": "campus.trashbin", "fields": {"token": "14B2GLA", "current_amount": 0, "total_amount": 10, "location_x": 4, "location_y": 0, "floor": 20, "created_at": "2022-07-28 11:04:05.684196", "updated_at": "2022-07-28 11:04:05.684196"}}, {"pk": 100, "model": "campus.trashbin", "fields": {"token": "14B2PPR", "current_amount": 0, "total_amount": 10, "location_x": 5, "location_y": 0, "floor": 20, "created_at": "2022-07-28 11:04:05.684196", "updated_at": "2022-07-28 11:04:05.684196"}}, {"pk": 101, "model": "campus.trashbin", "fields": {"token": "141GER", "current_amount": 0, "total_amount": 10, "location_x": 1, "location_y": 0, "floor": 21, "created_at": "2022-07-28 11:04:05.684196", "updated_at": "2022-07-28 11:04:05.684196"}}, {"pk": 102, "model": "campus.trashbin", "fields": {"token": "141PET", "current_amount": 0, "total_amount": 10, "location_x": 2, "location_y": 0, "floor": 21, "created_at": "2022-07-28 11:04:05.684196", "updated_at": "2022-07-28 11:04:05.684196"}}, {"pk": 103, "model": "campus.trashbin", "fields": {"token": "141CAN", "current_amount": 0, "total_amount": 10, "location_x": 3, "location_y": 0, "floor": 21, "created_at": "2022-07-28 11:04:05.684196", "updated_at": "2022-07-28 11:04:05.684196"}}, {"pk": 104, "model": "campus.trashbin", "fields": {"token": "141GLA", "current_amount": 0, "total_amount": 10, "location_x": 4, "location_y": 0, "floor": 21, "created_at": "2022-07-28 11:04:05.684196", "updated_at": "2022-07-28 11:04:05.684196"}}, {"pk": 105, "model": "campus.trashbin", "fields": {"token": "141PPR", "current_amount": 0, "total_amount": 10, "location_x": 5, "location_y": 0, "floor": 21, "created_at": "2022-07-28 11:04:05.684196", "updated_at": "2022-07-28 11:04:05.684196"}}, {"pk": 106, "model": "campus.trashbin", "fields": {"token": "142GER", "current_amount": 0, "total_amount": 10, "location_x": 1, "location_y": 0, "floor": 22, "created_at": "2022-07-28 11:04:05.684196", "updated_at": "2022-07-28 11:04:05.684196"}}, {"pk": 107, "model": "campus.trashbin", "fields": {"token": "142PET", "current_amount": 0, "total_amount": 10, "location_x": 2, "location_y": 0, "floor": 22, "created_at": "2022-07-28 11:04:05.684196", "updated_at": "2022-07-28 11:04:05.684196"}}, {"pk": 108, "model": "campus.trashbin", "fields": {"token": "142CAN", "current_amount": 0, "total_amount": 10, "location_x": 3, "location_y": 0, "floor": 22, "created_at": "2022-07-28 11:04:05.684196", "updated_at": "2022-07-28 11:04:05.684196"}}, {"pk": 109, "model": "campus.trashbin", "fields": {"token": "142GLA", "current_amount": 0, "total_amount": 10, "location_x": 4, "location_y": 0, "floor": 22, "created_at": "2022-07-28 11:04:05.684196", "updated_at": "2022-07-28 11:04:05.684196"}}, {"pk": 110, "model": "campus.trashbin", "fields": {"token": "142PPR", "current_amount": 0, "total_amount": 10, "location_x": 5, "location_y": 0, "floor": 22, "created_at": "2022-07-28 11:04:05.684196", "updated_at": "2022-07-28 11:04:05.684196"}}, {"pk": 111, "model": "campus.trashbin", "fields": {"token": "143GER", "current_amount": 0, "total_amount": 10, "location_x": 1, "location_y": 0, "floor": 23, "created_at": "2022-07-28 11:04:05.684196", "updated_at": "2022-07-28 11:04:05.684196"}}, {"pk": 112, "model": "campus.trashbin", "fields": {"token": "143PET", "current_amount": 0, "total_amount": 10, "location_x": 2, "location_y": 0, "floor": 23, "created_at": "2022-07-28 11:04:05.684196", "updated_at": "2022-07-28 11:04:05.684196"}}, {"pk": 113, "model": "campus.trashbin", "fields": {"token": "143CAN", "current_amount": 0, "total_amount": 10, "location_x": 3, "location_y": 0, "floor": 23, "created_at": "2022-07-28 11:04:05.684196", "updated_at": "2022-07-28 11:04:05.684196"}}, {"pk": 114, "model": "campus.trashbin", "fields": {"token": "143GLA", "current_amount": 0, "total_amount": 10, "location_x": 4, "location_y": 0, "floor": 23, "created_at": "2022-07-28 11:04:05.684196", "updated_at": "2022-07-28 11:04:05.684196"}}, {"pk": 115, "model": "campus.trashbin", "fields": {"token": "143PPR", "current_amount": 0, "total_amount": 10, "location_x": 5, "location_y": 0, "floor": 23, "created_at": "2022-07-28 11:04:05.684196", "updated_at": "2022-07-28 11:04:05.684196"}}, {"pk": 116, "model": "campus.trashbin", "fields": {"token": "144GER", "current_amount": 0, "total_amount": 10, "location_x": 1, "location_y": 0, "floor": 24, "created_at": "2022-07-28 11:04:05.684196", "updated_at": "2022-07-28 11:04:05.684196"}}, {"pk": 117, "model": "campus.trashbin", "fields": {"token": "144PET", "current_amount": 0, "total_amount": 10, "location_x": 2, "location_y": 0, "floor": 24, "created_at": "2022-07-28 11:04:05.684196", "updated_at": "2022-07-28 11:04:05.684196"}}, {"pk": 118, "model": "campus.trashbin", "fields": {"token": "144CAN", "current_amount": 0, "total_amount": 10, "location_x": 3, "location_y": 0, "floor": 24, "created_at": "2022-07-28 11:04:05.684196", "updated_at": "2022-07-28 11:04:05.684196"}}, {"pk": 119, "model": "campus.trashbin", "fields": {"token": "144GLA", "current_amount": 0, "total_amount": 10, "location_x": 4, "location_y": 0, "floor": 24, "created_at": "2022-07-28 11:04:05.684196", "updated_at": "2022-07-28 11:04:05.684196"}}, {"pk": 120, "model": "campus.trashbin", "fields": {"token": "144PPR", "current_amount": 0, "total_amount": 10, "location_x": 5, "location_y": 0, "floor": 24, "created_at": "2022-07-28 11:04:05.684196", "updated_at": "2022-07-28 11:04:05.684196"}}, {"pk": 121, "model": "campus.trashbin", "fields": {"token": "15B1GER", "current_amount": 0, "total_amount": 10, "location_x": 1, "location_y": 0, "floor": 25, "created_at": "2022-07-28 11:04:05.684196", "updated_at": "2022-07-28 11:04:05.684196"}}, {"pk": 122, "model": "campus.trashbin", "fields": {"token": "15B1PET", "current_amount": 0, "total_amount": 10, "location_x": 2, "location_y": 0, "floor": 25, "created_at": "2022-07-28 11:04:05.684196", "updated_at": "2022-07-28 11:04:05.684196"}}, {"pk": 123, "model": "campus.trashbin", "fields": {"token": "15B1CAN", "current_amount": 0, "total_amount": 10, "location_x": 3, "location_y": 0, "floor": 25, "created_at": "2022-07-28 11:04:05.684196", "updated_at": "2022-07-28 11:04:05.684196"}}, {"pk": 124, "model": "campus.trashbin", "fields": {"token": "15B1GLA", "current_amount": 0, "total_amount": 10, "location_x": 4, "location_y": 0, "floor": 25, "created_at": "2022-07-28 11:04:05.684196", "updated_at": "2022-07-28 11:04:05.684196"}}, {"pk": 125, "model": "campus.trashbin", "fields": {"token": "15B1PPR", "current_amount": 0, "total_amount": 10, "location_x": 5, "location_y": 0, "floor": 25, "created_at": "2022-07-28 11:04:05.684196", "updated_at": "2022-07-28 11:04:05.684196"}}, {"pk": 126, "model": "campus.trashbin", "fields": {"token": "15B2GER", "current_amount": 0, "total_amount": 10, "location_x": 1, "location_y": 0, "floor": 26, "created_at": "2022-07-28 11:04:05.684196", "updated_at": "2022-07-28 11:04:05.684196"}}, {"pk": 127, "model": "campus.trashbin", "fields": {"token": "15B2PET", "current_amount": 0, "total_amount": 10, "location_x": 2, "location_y": 0, "floor": 26, "created_at": "2022-07-28 11:04:05.684196", "updated_at": "2022-07-28 11:04:05.684196"}}, {"pk": 128, "model": "campus.trashbin", "fields": {"token": "15B2CAN", "current_amount": 0, "total_amount": 10, "location_x": 3, "location_y": 0, "floor": 26, "created_at": "2022-07-28 11:04:05.684196", "updated_at": "2022-07-28 11:04:05.684196"}}, {"pk": 129, "model": "campus.trashbin", "fields": {"token": "15B2GLA", "current_amount": 0, "total_amount": 10, "location_x": 4, "location_y": 0, "floor": 26, "created_at": "2022-07-28 11:04:05.684196", "updated_at": "2022-07-28 11:04:05.684196"}}, {"pk": 130, "model": "campus.trashbin", "fields": {"token": "15B2PPR", "current_amount": 0, "total_amount": 10, "location_x": 5, "location_y": 0, "floor": 26, "created_at": "2022-07-28 11:04:05.684196", "updated_at": "2022-07-28 11:04:05.684196"}}, {"pk": 131, "model": "campus.trashbin", "fields": {"token": "151GER", "current_amount": 0, "total_amount": 10, "location_x": 1, "location_y": 0, "floor": 27, "created_at": "2022-07-28 11:04:05.684196", "updated_at": "2022-07-28 11:04:05.684196"}}, {"pk": 132, "model": "campus.trashbin", "fields": {"token": "151PET", "current_amount": 0, "total_amount": 10, "location_x": 2, "location_y": 0, "floor": 27, "created_at": "2022-07-28 11:04:05.684196", "updated_at": "2022-07-28 11:04:05.684196"}}, {"pk": 133, "model": "campus.trashbin", "fields": {"token": "151CAN", "current_amount": 0, "total_amount": 10, "location_x": 3, "location_y": 0, "floor": 27, "created_at": "2022-07-28 11:04:05.684196", "updated_at": "2022-07-28 11:04:05.684196"}}, {"pk": 134, "model": "campus.trashbin", "fields": {"token": "151GLA", "current_amount": 0, "total_amount": 10, "location_x": 4, "location_y": 0, "floor": 27, "created_at": "2022-07-28 11:04:05.684196", "updated_at": "2022-07-28 11:04:05.684196"}}, {"pk": 135, "model": "campus.trashbin", "fields": {"token": "151PPR", "current_amount": 0, "total_amount": 10, "location_x": 5, "location_y": 0, "floor": 27, "created_at": "2022-07-28 11:04:05.684196", "updated_at": "2022-07-28 11:04:05.684196"}}, {"pk": 136, "model": "campus.trashbin", "fields": {"token": "152GER", "current_amount": 0, "total_amount": 10, "location_x": 1, "location_y": 0, "floor": 28, "created_at": "2022-07-28 11:04:05.684196", "updated_at": "2022-07-28 11:04:05.684196"}}, {"pk": 137, "model": "campus.trashbin", "fields": {"token": "152PET", "current_amount": 0, "total_amount": 10, "location_x": 2, "location_y": 0, "floor": 28, "created_at": "2022-07-28 11:04:05.684196", "updated_at": "2022-07-28 11:04:05.684196"}}, {"pk": 138, "model": "campus.trashbin", "fields": {"token": "152CAN", "current_amount": 0, "total_amount": 10, "location_x": 3, "location_y": 0, "floor": 28, "created_at": "2022-07-28 11:04:05.684196", "updated_at": "2022-07-28 11:04:05.684196"}}, {"pk": 139, "model": "campus.trashbin", "fields": {"token": "152GLA", "current_amount": 0, "total_amount": 10, "location_x": 4, "location_y": 0, "floor": 28, "created_at": "2022-07-28 11:04:05.684196", "updated_at": "2022-07-28 11:04:05.684196"}}, {"pk": 140, "model": "campus.trashbin", "fields": {"token": "152PPR", "current_amount": 0, "total_amount": 10, "location_x": 5, "location_y": 0, "floor": 28, "created_at": "2022-07-28 11:04:05.684196", "updated_at": "2022-07-28 11:04:05.684196"}}, {"pk": 141, "model": "campus.trashbin", "fields": {"token": "153GER", "current_amount": 0, "total_amount": 10, "location_x": 1, "location_y": 0, "floor": 29, "created_at": "2022-07-28 11:04:05.684196", "updated_at": "2022-07-28 11:04:05.684196"}}, {"pk": 142, "model": "campus.trashbin", "fields": {"token": "153PET", "current_amount": 0, "total_amount": 10, "location_x": 2, "location_y": 0, "floor": 29, "created_at": "2022-07-28 11:04:05.684196", "updated_at": "2022-07-28 11:04:05.684196"}}, {"pk": 143, "model": "campus.trashbin", "fields": {"token": "153CAN", "current_amount": 0, "total_amount": 10, "location_x": 3, "location_y": 0, "floor": 29, "created_at": "2022-07-28 11:04:05.684196", "updated_at": "2022-07-28 11:04:05.684196"}}, {"pk": 144, "model": "campus.trashbin", "fields": {"token": "153GLA", "current_amount": 0, "total_amount": 10, "location_x": 4, "location_y": 0, "floor": 29, "created_at": "2022-07-28 11:04:05.684196", "updated_at": "2022-07-28 11:04:05.684196"}}, {"pk": 145, "model": "campus.trashbin", "fields": {"token": "153PPR", "current_amount": 0, "total_amount": 10, "location_x": 5, "location_y": 0, "floor": 29, "created_at": "2022-07-28 11:04:05.684196", "updated_at": "2022-07-28 11:04:05.684196"}}, {"pk": 146, "model": "campus.trashbin", "fields": {"token": "154GER", "current_amount": 0, "total_amount": 10, "location_x": 1, "location_y": 0, "floor": 30, "created_at": "2022-07-28 11:04:05.684196", "updated_at": "2022-07-28 11:04:05.684196"}}, {"pk": 147, "model": "campus.trashbin", "fields": {"token": "154PET", "current_amount": 0, "total_amount": 10, "location_x": 2, "location_y": 0, "floor": 30, "created_at": "2022-07-28 11:04:05.684196", "updated_at": "2022-07-28 11:04:05.684196"}}, {"pk": 148, "model": "campus.trashbin", "fields": {"token": "154CAN", "current_amount": 0, "total_amount": 10, "location_x": 3, "location_y": 0, "floor": 30, "created_at": "2022-07-28 11:04:05.684196", "updated_at": "2022-07-28 11:04:05.684196"}}, {"pk": 149, "model": "campus.trashbin", "fields": {"token": "154GLA", "current_amount": 0, "total_amount": 10, "location_x": 4, "location_y": 0, "floor": 30, "created_at": "2022-07-28 11:04:05.684196", "updated_at": "2022-07-28 11:04:05.684196"}}, {"pk": 150, "model": "campus.trashbin", "fields": {"token": "154PPR", "current_amount": 0, "total_amount": 10, "location_x": 5, "location_y": 0, "floor": 30, "created_at": "2022-07-28 11:04:05.684196", "updated_at": "2022-07-28 11:04:05.684196"}}, {"pk": 151, "model": "campus.trashbin", "fields": {"token": "21B1GER", "current_amount": 0, "total_amount": 10, "location_x": 1, "location_y": 0, "floor": 31, "created_at": "2022-07-28 11:04:05.684196", "updated_at": "2022-07-28 11:04:05.684196"}}, {"pk": 152, "model": "campus.trashbin", "fields": {"token": "21B1PET", "current_amount": 0, "total_amount": 10, "location_x": 2, "location_y": 0, "floor": 31, "created_at": "2022-07-28 11:04:05.684196", "updated_at": "2022-07-28 11:04:05.684196"}}, {"pk": 153, "model": "campus.trashbin", "fields": {"token": "21B1CAN", "current_amount": 0, "total_amount": 10, "location_x": 3, "location_y": 0, "floor": 31, "created_at": "2022-07-28 11:04:05.684196", "updated_at": "2022-07-28 11:04:05.684196"}}, {"pk": 154, "model": "campus.trashbin", "fields": {"token": "21B1GLA", "current_amount": 0, "total_amount": 10, "location_x": 4, "location_y": 0, "floor": 31, "created_at": "2022-07-28 11:04:05.684196", "updated_at": "2022-07-28 11:04:05.684196"}}, {"pk": 155, "model": "campus.trashbin", "fields": {"token": "21B1PPR", "current_amount": 0, "total_amount": 10, "location_x": 5, "location_y": 0, "floor": 31, "created_at": "2022-07-28 11:04:05.684196", "updated_at": "2022-07-28 11:04:05.684196"}}, {"pk": 156, "model": "campus.trashbin", "fields": {"token": "21B2GER", "current_amount": 0, "total_amount": 10, "location_x": 1, "location_y": 0, "floor": 32, "created_at": "2022-07-28 11:04:05.684196", "updated_at": "2022-07-28 11:04:05.684196"}}, {"pk": 157, "model": "campus.trashbin", "fields": {"token": "21B2PET", "current_amount": 0, "total_amount": 10, "location_x": 2, "location_y": 0, "floor": 32, "created_at": "2022-07-28 11:04:05.684196", "updated_at": "2022-07-28 11:04:05.684196"}}, {"pk": 158, "model": "campus.trashbin", "fields": {"token": "21B2CAN", "current_amount": 0, "total_amount": 10, "location_x": 3, "location_y": 0, "floor": 32, "created_at": "2022-07-28 11:04:05.684196", "updated_at": "2022-07-28 11:04:05.684196"}}, {"pk": 159, "model": "campus.trashbin", "fields": {"token": "21B2GLA", "current_amount": 0, "total_amount": 10, "location_x": 4, "location_y": 0, "floor": 32, "created_at": "2022-07-28 11:04:05.684196", "updated_at": "2022-07-28 11:04:05.684196"}}, {"pk": 160, "model": "campus.trashbin", "fields": {"token": "21B2PPR", "current_amount": 0, "total_amount": 10, "location_x": 5, "location_y": 0, "floor": 32, "created_at": "2022-07-28 11:04:05.684196", "updated_at": "2022-07-28 11:04:05.684196"}}, {"pk": 161, "model": "campus.trashbin", "fields": {"token": "211GER", "current_amount": 0, "total_amount": 10, "location_x": 1, "location_y": 0, "floor": 33, "created_at": "2022-07-28 11:04:05.684196", "updated_at": "2022-07-28 11:04:05.684196"}}, {"pk": 162, "model": "campus.trashbin", "fields": {"token": "211PET", "current_amount": 0, "total_amount": 10, "location_x": 2, "location_y": 0, "floor": 33, "created_at": "2022-07-28 11:04:05.684196", "updated_at": "2022-07-28 11:04:05.684196"}}, {"pk": 163, "model": "campus.trashbin", "fields": {"token": "211CAN", "current_amount": 0, "total_amount": 10, "location_x": 3, "location_y": 0, "floor": 33, "created_at": "2022-07-28 11:04:05.684196", "updated_at": "2022-07-28 11:04:05.684196"}}, {"pk": 164, "model": "campus.trashbin", "fields": {"token": "211GLA", "current_amount": 0, "total_amount": 10, "location_x": 4, "location_y": 0, "floor": 33, "created_at": "2022-07-28 11:04:05.684196", "updated_at": "2022-07-28 11:04:05.684196"}}, {"pk": 165, "model": "campus.trashbin", "fields": {"token": "211PPR", "current_amount": 0, "total_amount": 10, "location_x": 5, "location_y": 0, "floor": 33, "created_at": "2022-07-28 11:04:05.684196", "updated_at": "2022-07-28 11:04:05.684196"}}, {"pk": 166, "model": "campus.trashbin", "fields": {"token": "212GER", "current_amount": 0, "total_amount": 10, "location_x": 1, "location_y": 0, "floor": 34, "created_at": "2022-07-28 11:04:05.684196", "updated_at": "2022-07-28 11:04:05.684196"}}, {"pk": 167, "model": "campus.trashbin", "fields": {"token": "212PET", "current_amount": 0, "total_amount": 10, "location_x": 2, "location_y": 0, "floor": 34, "created_at": "2022-07-28 11:04:05.684196", "updated_at": "2022-07-28 11:04:05.684196"}}, {"pk": 168, "model": "campus.trashbin", "fields": {"token": "212CAN", "current_amount": 0, "total_amount": 10, "location_x": 3, "location_y": 0, "floor": 34, "created_at": "2022-07-28 11:04:05.684196", "updated_at": "2022-07-28 11:04:05.684196"}}, {"pk": 169, "model": "campus.trashbin", "fields": {"token": "212GLA", "current_amount": 0, "total_amount": 10, "location_x": 4, "location_y": 0, "floor": 34, "created_at": "2022-07-28 11:04:05.684196", "updated_at": "2022-07-28 11:04:05.684196"}}, {"pk": 170, "model": "campus.trashbin", "fields": {"token": "212PPR", "current_amount": 0, "total_amount": 10, "location_x": 5, "location_y": 0, "floor": 34, "created_at": "2022-07-28 11:04:05.684196", "updated_at": "2022-07-28 11:04:05.684196"}}, {"pk": 171, "model": "campus.trashbin", "fields": {"token": "213GER", "current_amount": 0, "total_amount": 10, "location_x": 1, "location_y": 0, "floor": 35, "created_at": "2022-07-28 11:04:05.684196", "updated_at": "2022-07-28 11:04:05.684196"}}, {"pk": 172, "model": "campus.trashbin", "fields": {"token": "213PET", "current_amount": 0, "total_amount": 10, "location_x": 2, "location_y": 0, "floor": 35, "created_at": "2022-07-28 11:04:05.684196", "updated_at": "2022-07-28 11:04:05.684196"}}, {"pk": 173, "model": "campus.trashbin", "fields": {"token": "213CAN", "current_amount": 0, "total_amount": 10, "location_x": 3, "location_y": 0, "floor": 35, "created_at": "2022-07-28 11:04:05.684196", "updated_at": "2022-07-28 11:04:05.684196"}}, {"pk": 174, "model": "campus.trashbin", "fields": {"token": "213GLA", "current_amount": 0, "total_amount": 10, "location_x": 4, "location_y": 0, "floor": 35, "created_at": "2022-07-28 11:04:05.684196", "updated_at": "2022-07-28 11:04:05.684196"}}, {"pk": 175, "model": "campus.trashbin", "fields": {"token": "213PPR", "current_amount": 0, "total_amount": 10, "location_x": 5, "location_y": 0, "floor": 35, "created_at": "2022-07-28 11:04:05.684196", "updated_at": "2022-07-28 11:04:05.684196"}}, {"pk": 176, "model": "campus.trashbin", "fields": {"token": "214GER", "current_amount": 0, "total_amount": 10, "location_x": 1, "location_y": 0, "floor": 36, "created_at": "2022-07-28 11:04:05.684196", "updated_at": "2022-07-28 11:04:05.684196"}}, {"pk": 177, "model": "campus.trashbin", "fields": {"token": "214PET", "current_amount": 0, "total_amount": 10, "location_x": 2, "location_y": 0, "floor": 36, "created_at": "2022-07-28 11:04:05.684196", "updated_at": "2022-07-28 11:04:05.684196"}}, {"pk": 178, "model": "campus.trashbin", "fields": {"token": "214CAN", "current_amount": 0, "total_amount": 10, "location_x": 3, "location_y": 0, "floor": 36, "created_at": "2022-07-28 11:04:05.684196", "updated_at": "2022-07-28 11:04:05.684196"}}, {"pk": 179, "model": "campus.trashbin", "fields": {"token": "214GLA", "current_amount": 0, "total_amount": 10, "location_x": 4, "location_y": 0, "floor": 36, "created_at": "2022-07-28 11:04:05.684196", "updated_at": "2022-07-28 11:04:05.684196"}}, {"pk": 180, "model": "campus.trashbin", "fields": {"token": "214PPR", "current_amount": 0, "total_amount": 10, "location_x": 5, "location_y": 0, "floor": 36, "created_at": "2022-07-28 11:04:05.684196", "updated_at": "2022-07-28 11:04:05.684196"}}, {"pk": 181, "model": "campus.trashbin", "fields": {"token": "22B1GER", "current_amount": 0, "total_amount": 10, "location_x": 1, "location_y": 0, "floor": 37, "created_at": "2022-07-28 11:04:05.684196", "updated_at": "2022-07-28 11:04:05.684196"}}, {"pk": 182, "model": "campus.trashbin", "fields": {"token": "22B1PET", "current_amount": 0, "total_amount": 10, "location_x": 2, "location_y": 0, "floor": 37, "created_at": "2022-07-28 11:04:05.684196", "updated_at": "2022-07-28 11:04:05.684196"}}, {"pk": 183, "model": "campus.trashbin", "fields": {"token": "22B1CAN", "current_amount": 0, "total_amount": 10, "location_x": 3, "location_y": 0, "floor": 37, "created_at": "2022-07-28 11:04:05.684196", "updated_at": "2022-07-28 11:04:05.684196"}}, {"pk": 184, "model": "campus.trashbin", "fields": {"token": "22B1GLA", "current_amount": 0, "total_amount": 10, "location_x": 4, "location_y": 0, "floor": 37, "created_at": "2022-07-28 11:04:05.684196", "updated_at": "2022-07-28 11:04:05.684196"}}, {"pk": 185, "model": "campus.trashbin", "fields": {"token": "22B1PPR", "current_amount": 0, "total_amount": 10, "location_x": 5, "location_y": 0, "floor": 37, "created_at": "2022-07-28 11:04:05.684196", "updated_at": "2022-07-28 11:04:05.684196"}}, {"pk": 186, "model": "campus.trashbin", "fields": {"token": "22B2GER", "current_amount": 0, "total_amount": 10, "location_x": 1, "location_y": 0, "floor": 38, "created_at": "2022-07-28 11:04:05.684196", "updated_at": "2022-07-28 11:04:05.684196"}}, {"pk": 187, "model": "campus.trashbin", "fields": {"token": "22B2PET", "current_amount": 0, "total_amount": 10, "location_x": 2, "location_y": 0, "floor": 38, "created_at": "2022-07-28 11:04:05.684196", "updated_at": "2022-07-28 11:04:05.684196"}}, {"pk": 188, "model": "campus.trashbin", "fields": {"token": "22B2CAN", "current_amount": 0, "total_amount": 10, "location_x": 3, "location_y": 0, "floor": 38, "created_at": "2022-07-28 11:04:05.684196", "updated_at": "2022-07-28 11:04:05.684196"}}, {"pk": 189, "model": "campus.trashbin", "fields": {"token": "22B2GLA", "current_amount": 0, "total_amount": 10, "location_x": 4, "location_y": 0, "floor": 38, "created_at": "2022-07-28 11:04:05.684196", "updated_at": "2022-07-28 11:04:05.684196"}}, {"pk": 190, "model": "campus.trashbin", "fields": {"token": "22B2PPR", "current_amount": 0, "total_amount": 10, "location_x": 5, "location_y": 0, "floor": 38, "created_at": "2022-07-28 11:04:05.684196", "updated_at": "2022-07-28 11:04:05.684196"}}, {"pk": 191, "model": "campus.trashbin", "fields": {"token": "221GER", "current_amount": 0, "total_amount": 10, "location_x": 1, "location_y": 0, "floor": 39, "created_at": "2022-07-28 11:04:05.684196", "updated_at": "2022-07-28 11:04:05.684196"}}, {"pk": 192, "model": "campus.trashbin", "fields": {"token": "221PET", "current_amount": 0, "total_amount": 10, "location_x": 2, "location_y": 0, "floor": 39, "created_at": "2022-07-28 11:04:05.684196", "updated_at": "2022-07-28 11:04:05.684196"}}, {"pk": 193, "model": "campus.trashbin", "fields": {"token": "221CAN", "current_amount": 0, "total_amount": 10, "location_x": 3, "location_y": 0, "floor": 39, "created_at": "2022-07-28 11:04:05.684196", "updated_at": "2022-07-28 11:04:05.684196"}}, {"pk": 194, "model": "campus.trashbin", "fields": {"token": "221GLA", "current_amount": 0, "total_amount": 10, "location_x": 4, "location_y": 0, "floor": 39, "created_at": "2022-07-28 11:04:05.684196", "updated_at": "2022-07-28 11:04:05.684196"}}, {"pk": 195, "model": "campus.trashbin", "fields": {"token": "221PPR", "current_amount": 0, "total_amount": 10, "location_x": 5, "location_y": 0, "floor": 39, "created_at": "2022-07-28 11:04:05.684196", "updated_at": "2022-07-28 11:04:05.684196"}}, {"pk": 196, "model": "campus.trashbin", "fields": {"token": "222GER", "current_amount": 0, "total_amount": 10, "location_x": 1, "location_y": 0, "floor": 40, "created_at": "2022-07-28 11:04:05.684196", "updated_at": "2022-07-28 11:04:05.684196"}}, {"pk": 197, "model": "campus.trashbin", "fields": {"token": "222PET", "current_amount": 0, "total_amount": 10, "location_x": 2, "location_y": 0, "floor": 40, "created_at": "2022-07-28 11:04:05.684196", "updated_at": "2022-07-28 11:04:05.684196"}}, {"pk": 198, "model": "campus.trashbin", "fields": {"token": "222CAN", "current_amount": 0, "total_amount": 10, "location_x": 3, "location_y": 0, "floor": 40, "created_at": "2022-07-28 11:04:05.684196", "updated_at": "2022-07-28 11:04:05.684196"}}, {"pk": 199, "model": "campus.trashbin", "fields": {"token": "222GLA", "current_amount": 0, "total_amount": 10, "location_x": 4, "location_y": 0, "floor": 40, "created_at": "2022-07-28 11:04:05.684196", "updated_at": "2022-07-28 11:04:05.684196"}}, {"pk": 200, "model": "campus.trashbin", "fields": {"token": "222PPR", "current_amount": 0, "total_amount": 10, "location_x": 5, "location_y": 0, "floor": 40, "created_at": "2022-07-28 11:04:05.684196", "updated_at": "2022-07-28 11:04:05.684196"}}, {"pk": 201, "model": "campus.trashbin", "fields": {"token": "223GER", "current_amount": 0, "total_amount": 10, "location_x": 1, "location_y": 0, "floor": 41, "created_at": "2022-07-28 11:04:05.684196", "updated_at": "2022-07-28 11:04:05.684196"}}, {"pk": 202, "model": "campus.trashbin", "fields": {"token": "223PET", "current_amount": 0, "total_amount": 10, "location_x": 2, "location_y": 0, "floor": 41, "created_at": "2022-07-28 11:04:05.684196", "updated_at": "2022-07-28 11:04:05.684196"}}, {"pk": 203, "model": "campus.trashbin", "fields": {"token": "223CAN", "current_amount": 0, "total_amount": 10, "location_x": 3, "location_y": 0, "floor": 41, "created_at": "2022-07-28 11:04:05.684196", "updated_at": "2022-07-28 11:04:05.684196"}}, {"pk": 204, "model": "campus.trashbin", "fields": {"token": "223GLA", "current_amount": 0, "total_amount": 10, "location_x": 4, "location_y": 0, "floor": 41, "created_at": "2022-07-28 11:04:05.684196", "updated_at": "2022-07-28 11:04:05.684196"}}, {"pk": 205, "model": "campus.trashbin", "fields": {"token": "223PPR", "current_amount": 0, "total_amount": 10, "location_x": 5, "location_y": 0, "floor": 41, "created_at": "2022-07-28 11:04:05.684196", "updated_at": "2022-07-28 11:04:05.684196"}}, {"pk": 206, "model": "campus.trashbin", "fields": {"token": "224GER", "current_amount": 0, "total_amount": 10, "location_x": 1, "location_y": 0, "floor": 42, "created_at": "2022-07-28 11:04:05.684196", "updated_at": "2022-07-28 11:04:05.684196"}}, {"pk": 207, "model": "campus.trashbin", "fields": {"token": "224PET", "current_amount": 0, "total_amount": 10, "location_x": 2, "location_y": 0, "floor": 42, "created_at": "2022-07-28 11:04:05.684196", "updated_at": "2022-07-28 11:04:05.684196"}}, {"pk": 208, "model": "campus.trashbin", "fields": {"token": "224CAN", "current_amount": 0, "total_amount": 10, "location_x": 3, "location_y": 0, "floor": 42, "created_at": "2022-07-28 11:04:05.684196", "updated_at": "2022-07-28 11:04:05.684196"}}, {"pk": 209, "model": "campus.trashbin", "fields": {"token": "224GLA", "current_amount": 0, "total_amount": 10, "location_x": 4, "location_y": 0, "floor": 42, "created_at": "2022-07-28 11:04:05.684196", "updated_at": "2022-07-28 11:04:05.684196"}}, {"pk": 210, "model": "campus.trashbin", "fields": {"token": "224PPR", "current_amount": 0, "total_amount": 10, "location_x": 5, "location_y": 0, "floor": 42, "created_at": "2022-07-28 11:04:05.684196", "updated_at": "2022-07-28 11:04:05.684196"}}, {"pk": 211, "model": "campus.trashbin", "fields": {"token": "23B1GER", "current_amount": 0, "total_amount": 10, "location_x": 1, "location_y": 0, "floor": 43, "created_at": "2022-07-28 11:04:05.684196", "updated_at": "2022-07-28 11:04:05.684196"}}, {"pk": 212, "model": "campus.trashbin", "fields": {"token": "23B1PET", "current_amount": 0, "total_amount": 10, "location_x": 2, "location_y": 0, "floor": 43, "created_at": "2022-07-28 11:04:05.684196", "updated_at": "2022-07-28 11:04:05.684196"}}, {"pk": 213, "model": "campus.trashbin", "fields": {"token": "23B1CAN", "current_amount": 0, "total_amount": 10, "location_x": 3, "location_y": 0, "floor": 43, "created_at": "2022-07-28 11:04:05.684196", "updated_at": "2022-07-28 11:04:05.684196"}}, {"pk": 214, "model": "campus.trashbin", "fields": {"token": "23B1GLA", "current_amount": 0, "total_amount": 10, "location_x": 4, "location_y": 0, "floor": 43, "created_at": "2022-07-28 11:04:05.684196", "updated_at": "2022-07-28 11:04:05.684196"}}, {"pk": 215, "model": "campus.trashbin", "fields": {"token": "23B1PPR", "current_amount": 0, "total_amount": 10, "location_x": 5, "location_y": 0, "floor": 43, "created_at": "2022-07-28 11:04:05.684196", "updated_at": "2022-07-28 11:04:05.684196"}}, {"pk": 216, "model": "campus.trashbin", "fields": {"token": "23B2GER", "current_amount": 0, "total_amount": 10, "location_x": 1, "location_y": 0, "floor": 44, "created_at": "2022-07-28 11:04:05.684196", "updated_at": "2022-07-28 11:04:05.684196"}}, {"pk": 217, "model": "campus.trashbin", "fields": {"token": "23B2PET", "current_amount": 0, "total_amount": 10, "location_x": 2, "location_y": 0, "floor": 44, "created_at": "2022-07-28 11:04:05.684196", "updated_at": "2022-07-28 11:04:05.684196"}}, {"pk": 218, "model": "campus.trashbin", "fields": {"token": "23B2CAN", "current_amount": 0, "total_amount": 10, "location_x": 3, "location_y": 0, "floor": 44, "created_at": "2022-07-28 11:04:05.684196", "updated_at": "2022-07-28 11:04:05.684196"}}, {"pk": 219, "model": "campus.trashbin", "fields": {"token": "23B2GLA", "current_amount": 0, "total_amount": 10, "location_x": 4, "location_y": 0, "floor": 44, "created_at": "2022-07-28 11:04:05.684196", "updated_at": "2022-07-28 11:04:05.684196"}}, {"pk": 220, "model": "campus.trashbin", "fields": {"token": "23B2PPR", "current_amount": 0, "total_amount": 10, "location_x": 5, "location_y": 0, "floor": 44, "created_at": "2022-07-28 11:04:05.684196", "updated_at": "2022-07-28 11:04:05.684196"}}, {"pk": 221, "model": "campus.trashbin", "fields": {"token": "231GER", "current_amount": 0, "total_amount": 10, "location_x": 1, "location_y": 0, "floor": 45, "created_at": "2022-07-28 11:04:05.684196", "updated_at": "2022-07-28 11:04:05.684196"}}, {"pk": 222, "model": "campus.trashbin", "fields": {"token": "231PET", "current_amount": 0, "total_amount": 10, "location_x": 2, "location_y": 0, "floor": 45, "created_at": "2022-07-28 11:04:05.684196", "updated_at": "2022-07-28 11:04:05.684196"}}, {"pk": 223, "model": "campus.trashbin", "fields": {"token": "231CAN", "current_amount": 0, "total_amount": 10, "location_x": 3, "location_y": 0, "floor": 45, "created_at": "2022-07-28 11:04:05.684196", "updated_at": "2022-07-28 11:04:05.684196"}}, {"pk": 224, "model": "campus.trashbin", "fields": {"token": "231GLA", "current_amount": 0, "total_amount": 10, "location_x": 4, "location_y": 0, "floor": 45, "created_at": "2022-07-28 11:04:05.684196", "updated_at": "2022-07-28 11:04:05.684196"}}, {"pk": 225, "model": "campus.trashbin", "fields": {"token": "231PPR", "current_amount": 0, "total_amount": 10, "location_x": 5, "location_y": 0, "floor": 45, "created_at": "2022-07-28 11:04:05.684196", "updated_at": "2022-07-28 11:04:05.684196"}}, {"pk": 226, "model": "campus.trashbin", "fields": {"token": "232GER", "current_amount": 0, "total_amount": 10, "location_x": 1, "location_y": 0, "floor": 46, "created_at": "2022-07-28 11:04:05.684196", "updated_at": "2022-07-28 11:04:05.684196"}}, {"pk": 227, "model": "campus.trashbin", "fields": {"token": "232PET", "current_amount": 0, "total_amount": 10, "location_x": 2, "location_y": 0, "floor": 46, "created_at": "2022-07-28 11:04:05.684196", "updated_at": "2022-07-28 11:04:05.684196"}}, {"pk": 228, "model": "campus.trashbin", "fields": {"token": "232CAN", "current_amount": 0, "total_amount": 10, "location_x": 3, "location_y": 0, "floor": 46, "created_at": "2022-07-28 11:04:05.684196", "updated_at": "2022-07-28 11:04:05.684196"}}, {"pk": 229, "model": "campus.trashbin", "fields": {"token": "232GLA", "current_amount": 0, "total_amount": 10, "location_x": 4, "location_y": 0, "floor": 46, "created_at": "2022-07-28 11:04:05.684196", "updated_at": "2022-07-28 11:04:05.684196"}}, {"pk": 230, "model": "campus.trashbin", "fields": {"token": "232PPR", "current_amount": 0, "total_amount": 10, "location_x": 5, "location_y": 0, "floor": 46, "created_at": "2022-07-28 11:04:05.684196", "updated_at": "2022-07-28 11:04:05.684196"}}, {"pk": 231, "model": "campus.trashbin", "fields": {"token": "233GER", "current_amount": 0, "total_amount": 10, "location_x": 1, "location_y": 0, "floor": 47, "created_at": "2022-07-28 11:04:05.684196", "updated_at": "2022-07-28 11:04:05.684196"}}, {"pk": 232, "model": "campus.trashbin", "fields": {"token": "233PET", "current_amount": 0, "total_amount": 10, "location_x": 2, "location_y": 0, "floor": 47, "created_at": "2022-07-28 11:04:05.684196", "updated_at": "2022-07-28 11:04:05.684196"}}, {"pk": 233, "model": "campus.trashbin", "fields": {"token": "233CAN", "current_amount": 0, "total_amount": 10, "location_x": 3, "location_y": 0, "floor": 47, "created_at": "2022-07-28 11:04:05.684196", "updated_at": "2022-07-28 11:04:05.684196"}}, {"pk": 234, "model": "campus.trashbin", "fields": {"token": "233GLA", "current_amount": 0, "total_amount": 10, "location_x": 4, "location_y": 0, "floor": 47, "created_at": "2022-07-28 11:04:05.684196", "updated_at": "2022-07-28 11:04:05.684196"}}, {"pk": 235, "model": "campus.trashbin", "fields": {"token": "233PPR", "current_amount": 0, "total_amount": 10, "location_x": 5, "location_y": 0, "floor": 47, "created_at": "2022-07-28 11:04:05.684196", "updated_at": "2022-07-28 11:04:05.684196"}}, {"pk": 236, "model": "campus.trashbin", "fields": {"token": "234GER", "current_amount": 0, "total_amount": 10, "location_x": 1, "location_y": 0, "floor": 48, "created_at": "2022-07-28 11:04:05.684196", "updated_at": "2022-07-28 11:04:05.684196"}}, {"pk": 237, "model": "campus.trashbin", "fields": {"token": "234PET", "current_amount": 0, "total_amount": 10, "location_x": 2, "location_y": 0, "floor": 48, "created_at": "2022-07-28 11:04:05.684196", "updated_at": "2022-07-28 11:04:05.684196"}}, {"pk": 238, "model": "campus.trashbin", "fields": {"token": "234CAN", "current_amount": 0, "total_amount": 10, "location_x": 3, "location_y": 0, "floor": 48, "created_at": "2022-07-28 11:04:05.684196", "updated_at": "2022-07-28 11:04:05.684196"}}, {"pk": 239, "model": "campus.trashbin", "fields": {"token": "234GLA", "current_amount": 0, "total_amount": 10, "location_x": 4, "location_y": 0, "floor": 48, "created_at": "2022-07-28 11:04:05.684196", "updated_at": "2022-07-28 11:04:05.684196"}}, {"pk": 240, "model": "campus.trashbin", "fields": {"token": "234PPR", "current_amount": 0, "total_amount": 10, "location_x": 5, "location_y": 0, "floor": 48, "created_at": "2022-07-28 11:04:05.684196", "updated_at": "2022-07-28 11:04:05.684196"}}, {"pk": 241, "model": "campus.trashbin", "fields": {"token": "24B1GER", "current_amount": 0, "total_amount": 10, "location_x": 1, "location_y": 0, "floor": 49, "created_at": "2022-07-28 11:04:05.684196", "updated_at": "2022-07-28 11:04:05.684196"}}, {"pk": 242, "model": "campus.trashbin", "fields": {"token": "24B1PET", "current_amount": 0, "total_amount": 10, "location_x": 2, "location_y": 0, "floor": 49, "created_at": "2022-07-28 11:04:05.684196", "updated_at": "2022-07-28 11:04:05.684196"}}, {"pk": 243, "model": "campus.trashbin", "fields": {"token": "24B1CAN", "current_amount": 0, "total_amount": 10, "location_x": 3, "location_y": 0, "floor": 49, "created_at": "2022-07-28 11:04:05.684196", "updated_at": "2022-07-28 11:04:05.684196"}}, {"pk": 244, "model": "campus.trashbin", "fields": {"token": "24B1GLA", "current_amount": 0, "total_amount": 10, "location_x": 4, "location_y": 0, "floor": 49, "created_at": "2022-07-28 11:04:05.684196", "updated_at": "2022-07-28 11:04:05.684196"}}, {"pk": 245, "model": "campus.trashbin", "fields": {"token": "24B1PPR", "current_amount": 0, "total_amount": 10, "location_x": 5, "location_y": 0, "floor": 49, "created_at": "2022-07-28 11:04:05.684196", "updated_at": "2022-07-28 11:04:05.684196"}}, {"pk": 246, "model": "campus.trashbin", "fields": {"token": "24B2GER", "current_amount": 0, "total_amount": 10, "location_x": 1, "location_y": 0, "floor": 50, "created_at": "2022-07-28 11:04:05.684196", "updated_at": "2022-07-28 11:04:05.684196"}}, {"pk": 247, "model": "campus.trashbin", "fields": {"token": "24B2PET", "current_amount": 0, "total_amount": 10, "location_x": 2, "location_y": 0, "floor": 50, "created_at": "2022-07-28 11:04:05.684196", "updated_at": "2022-07-28 11:04:05.684196"}}, {"pk": 248, "model": "campus.trashbin", "fields": {"token": "24B2CAN", "current_amount": 0, "total_amount": 10, "location_x": 3, "location_y": 0, "floor": 50, "created_at": "2022-07-28 11:04:05.684196", "updated_at": "2022-07-28 11:04:05.684196"}}, {"pk": 249, "model": "campus.trashbin", "fields": {"token": "24B2GLA", "current_amount": 0, "total_amount": 10, "location_x": 4, "location_y": 0, "floor": 50, "created_at": "2022-07-28 11:04:05.684196", "updated_at": "2022-07-28 11:04:05.684196"}}, {"pk": 250, "model": "campus.trashbin", "fields": {"token": "24B2PPR", "current_amount": 0, "total_amount": 10, "location_x": 5, "location_y": 0, "floor": 50, "created_at": "2022-07-28 11:04:05.684196", "updated_at": "2022-07-28 11:04:05.684196"}}, {"pk": 251, "model": "campus.trashbin", "fields": {"token": "241GER", "current_amount": 0, "total_amount": 10, "location_x": 1, "location_y": 0, "floor": 51, "created_at": "2022-07-28 11:04:05.684196", "updated_at": "2022-07-28 11:04:05.684196"}}, {"pk": 252, "model": "campus.trashbin", "fields": {"token": "241PET", "current_amount": 0, "total_amount": 10, "location_x": 2, "location_y": 0, "floor": 51, "created_at": "2022-07-28 11:04:05.684196", "updated_at": "2022-07-28 11:04:05.684196"}}, {"pk": 253, "model": "campus.trashbin", "fields": {"token": "241CAN", "current_amount": 0, "total_amount": 10, "location_x": 3, "location_y": 0, "floor": 51, "created_at": "2022-07-28 11:04:05.684196", "updated_at": "2022-07-28 11:04:05.684196"}}, {"pk": 254, "model": "campus.trashbin", "fields": {"token": "241GLA", "current_amount": 0, "total_amount": 10, "location_x": 4, "location_y": 0, "floor": 51, "created_at": "2022-07-28 11:04:05.684196", "updated_at": "2022-07-28 11:04:05.684196"}}, {"pk": 255, "model": "campus.trashbin", "fields": {"token": "241PPR", "current_amount": 0, "total_amount": 10, "location_x": 5, "location_y": 0, "floor": 51, "created_at": "2022-07-28 11:04:05.684196", "updated_at": "2022-07-28 11:04:05.684196"}}, {"pk": 256, "model": "campus.trashbin", "fields": {"token": "242GER", "current_amount": 0, "total_amount": 10, "location_x": 1, "location_y": 0, "floor": 52, "created_at": "2022-07-28 11:04:05.684196", "updated_at": "2022-07-28 11:04:05.684196"}}, {"pk": 257, "model": "campus.trashbin", "fields": {"token": "242PET", "current_amount": 0, "total_amount": 10, "location_x": 2, "location_y": 0, "floor": 52, "created_at": "2022-07-28 11:04:05.684196", "updated_at": "2022-07-28 11:04:05.684196"}}, {"pk": 258, "model": "campus.trashbin", "fields": {"token": "242CAN", "current_amount": 0, "total_amount": 10, "location_x": 3, "location_y": 0, "floor": 52, "created_at": "2022-07-28 11:04:05.684196", "updated_at": "2022-07-28 11:04:05.684196"}}, {"pk": 259, "model": "campus.trashbin", "fields": {"token": "242GLA", "current_amount": 0, "total_amount": 10, "location_x": 4, "location_y": 0, "floor": 52, "created_at": "2022-07-28 11:04:05.684196", "updated_at": "2022-07-28 11:04:05.684196"}}, {"pk": 260, "model": "campus.trashbin", "fields": {"token": "242PPR", "current_amount": 0, "total_amount": 10, "location_x": 5, "location_y": 0, "floor": 52, "created_at": "2022-07-28 11:04:05.684196", "updated_at": "2022-07-28 11:04:05.684196"}}, {"pk": 261, "model": "campus.trashbin", "fields": {"token": "243GER", "current_amount": 0, "total_amount": 10, "location_x": 1, "location_y": 0, "floor": 53, "created_at": "2022-07-28 11:04:05.684196", "updated_at": "2022-07-28 11:04:05.684196"}}, {"pk": 262, "model": "campus.trashbin", "fields": {"token": "243PET", "current_amount": 0, "total_amount": 10, "location_x": 2, "location_y": 0, "floor": 53, "created_at": "2022-07-28 11:04:05.684196", "updated_at": "2022-07-28 11:04:05.684196"}}, {"pk": 263, "model": "campus.trashbin", "fields": {"token": "243CAN", "current_amount": 0, "total_amount": 10, "location_x": 3, "location_y": 0, "floor": 53, "created_at": "2022-07-28 11:04:05.684196", "updated_at": "2022-07-28 11:04:05.684196"}}, {"pk": 264, "model": "campus.trashbin", "fields": {"token": "243GLA", "current_amount": 0, "total_amount": 10, "location_x": 4, "location_y": 0, "floor": 53, "created_at": "2022-07-28 11:04:05.684196", "updated_at": "2022-07-28 11:04:05.684196"}}, {"pk": 265, "model": "campus.trashbin", "fields": {"token": "243PPR", "current_amount": 0, "total_amount": 10, "location_x": 5, "location_y": 0, "floor": 53, "created_at": "2022-07-28 11:04:05.684196", "updated_at": "2022-07-28 11:04:05.684196"}}, {"pk": 266, "model": "campus.trashbin", "fields": {"token": "244GER", "current_amount": 0, "total_amount": 10, "location_x": 1, "location_y": 0, "floor": 54, "created_at": "2022-07-28 11:04:05.684196", "updated_at": "2022-07-28 11:04:05.684196"}}, {"pk": 267, "model": "campus.trashbin", "fields": {"token": "244PET", "current_amount": 0, "total_amount": 10, "location_x": 2, "location_y": 0, "floor": 54, "created_at": "2022-07-28 11:04:05.684196", "updated_at": "2022-07-28 11:04:05.684196"}}, {"pk": 268, "model": "campus.trashbin", "fields": {"token": "244CAN", "current_amount": 0, "total_amount": 10, "location_x": 3, "location_y": 0, "floor": 54, "created_at": "2022-07-28 11:04:05.684196", "updated_at": "2022-07-28 11:04:05.684196"}}, {"pk": 269, "model": "campus.trashbin", "fields": {"token": "244GLA", "current_amount": 0, "total_amount": 10, "location_x": 4, "location_y": 0, "floor": 54, "created_at": "2022-07-28 11:04:05.684196", "updated_at": "2022-07-28 11:04:05.684196"}}, {"pk": 270, "model": "campus.trashbin", "fields": {"token": "244PPR", "current_amount": 0, "total_amount": 10, "location_x": 5, "location_y": 0, "floor": 54, "created_at": "2022-07-28 11:04:05.684196", "updated_at": "2022-07-28 11:04:05.684196"}}, {"pk": 271, "model": "campus.trashbin", "fields": {"token": "25B1GER", "current_amount": 0, "total_amount": 10, "location_x": 1, "location_y": 0, "floor": 55, "created_at": "2022-07-28 11:04:05.684196", "updated_at": "2022-07-28 11:04:05.684196"}}, {"pk": 272, "model": "campus.trashbin", "fields": {"token": "25B1PET", "current_amount": 0, "total_amount": 10, "location_x": 2, "location_y": 0, "floor": 55, "created_at": "2022-07-28 11:04:05.684196", "updated_at": "2022-07-28 11:04:05.684196"}}, {"pk": 273, "model": "campus.trashbin", "fields": {"token": "25B1CAN", "current_amount": 0, "total_amount": 10, "location_x": 3, "location_y": 0, "floor": 55, "created_at": "2022-07-28 11:04:05.684196", "updated_at": "2022-07-28 11:04:05.684196"}}, {"pk": 274, "model": "campus.trashbin", "fields": {"token": "25B1GLA", "current_amount": 0, "total_amount": 10, "location_x": 4, "location_y": 0, "floor": 55, "created_at": "2022-07-28 11:04:05.684196", "updated_at": "2022-07-28 11:04:05.684196"}}, {"pk": 275, "model": "campus.trashbin", "fields": {"token": "25B1PPR", "current_amount": 0, "total_amount": 10, "location_x": 5, "location_y": 0, "floor": 55, "created_at": "2022-07-28 11:04:05.684196", "updated_at": "2022-07-28 11:04:05.684196"}}, {"pk": 276, "model": "campus.trashbin", "fields": {"token": "25B2GER", "current_amount": 0, "total_amount": 10, "location_x": 1, "location_y": 0, "floor": 56, "created_at": "2022-07-28 11:04:05.684196", "updated_at": "2022-07-28 11:04:05.684196"}}, {"pk": 277, "model": "campus.trashbin", "fields": {"token": "25B2PET", "current_amount": 0, "total_amount": 10, "location_x": 2, "location_y": 0, "floor": 56, "created_at": "2022-07-28 11:04:05.684196", "updated_at": "2022-07-28 11:04:05.684196"}}, {"pk": 278, "model": "campus.trashbin", "fields": {"token": "25B2CAN", "current_amount": 0, "total_amount": 10, "location_x": 3, "location_y": 0, "floor": 56, "created_at": "2022-07-28 11:04:05.684196", "updated_at": "2022-07-28 11:04:05.684196"}}, {"pk": 279, "model": "campus.trashbin", "fields": {"token": "25B2GLA", "current_amount": 0, "total_amount": 10, "location_x": 4, "location_y": 0, "floor": 56, "created_at": "2022-07-28 11:04:05.684196", "updated_at": "2022-07-28 11:04:05.684196"}}, {"pk": 280, "model": "campus.trashbin", "fields": {"token": "25B2PPR", "current_amount": 0, "total_amount": 10, "location_x": 5, "location_y": 0, "floor": 56, "created_at": "2022-07-28 11:04:05.684196", "updated_at": "2022-07-28 11:04:05.684196"}}, {"pk": 281, "model": "campus.trashbin", "fields": {"token": "251GER", "current_amount": 0, "total_amount": 10, "location_x": 1, "location_y": 0, "floor": 57, "created_at": "2022-07-28 11:04:05.684196", "updated_at": "2022-07-28 11:04:05.684196"}}, {"pk": 282, "model": "campus.trashbin", "fields": {"token": "251PET", "current_amount": 0, "total_amount": 10, "location_x": 2, "location_y": 0, "floor": 57, "created_at": "2022-07-28 11:04:05.684196", "updated_at": "2022-07-28 11:04:05.684196"}}, {"pk": 283, "model": "campus.trashbin", "fields": {"token": "251CAN", "current_amount": 0, "total_amount": 10, "location_x": 3, "location_y": 0, "floor": 57, "created_at": "2022-07-28 11:04:05.684196", "updated_at": "2022-07-28 11:04:05.684196"}}, {"pk": 284, "model": "campus.trashbin", "fields": {"token": "251GLA", "current_amount": 0, "total_amount": 10, "location_x": 4, "location_y": 0, "floor": 57, "created_at": "2022-07-28 11:04:05.684196", "updated_at": "2022-07-28 11:04:05.684196"}}, {"pk": 285, "model": "campus.trashbin", "fields": {"token": "251PPR", "current_amount": 0, "total_amount": 10, "location_x": 5, "location_y": 0, "floor": 57, "created_at": "2022-07-28 11:04:05.684196", "updated_at": "2022-07-28 11:04:05.684196"}}, {"pk": 286, "model": "campus.trashbin", "fields": {"token": "252GER", "current_amount": 0, "total_amount": 10, "location_x": 1, "location_y": 0, "floor": 58, "created_at": "2022-07-28 11:04:05.684196", "updated_at": "2022-07-28 11:04:05.684196"}}, {"pk": 287, "model": "campus.trashbin", "fields": {"token": "252PET", "current_amount": 0, "total_amount": 10, "location_x": 2, "location_y": 0, "floor": 58, "created_at": "2022-07-28 11:04:05.684196", "updated_at": "2022-07-28 11:04:05.684196"}}, {"pk": 288, "model": "campus.trashbin", "fields": {"token": "252CAN", "current_amount": 0, "total_amount": 10, "location_x": 3, "location_y": 0, "floor": 58, "created_at": "2022-07-28 11:04:05.684196", "updated_at": "2022-07-28 11:04:05.684196"}}, {"pk": 289, "model": "campus.trashbin", "fields": {"token": "252GLA", "current_amount": 0, "total_amount": 10, "location_x": 4, "location_y": 0, "floor": 58, "created_at": "2022-07-28 11:04:05.684196", "updated_at": "2022-07-28 11:04:05.684196"}}, {"pk": 290, "model": "campus.trashbin", "fields": {"token": "252PPR", "current_amount": 0, "total_amount": 10, "location_x": 5, "location_y": 0, "floor": 58, "created_at": "2022-07-28 11:04:05.684196", "updated_at": "2022-07-28 11:04:05.684196"}}, {"pk": 291, "model": "campus.trashbin", "fields": {"token": "253GER", "current_amount": 0, "total_amount": 10, "location_x": 1, "location_y": 0, "floor": 59, "created_at": "2022-07-28 11:04:05.684196", "updated_at": "2022-07-28 11:04:05.684196"}}, {"pk": 292, "model": "campus.trashbin", "fields": {"token": "253PET", "current_amount": 0, "total_amount": 10, "location_x": 2, "location_y": 0, "floor": 59, "created_at": "2022-07-28 11:04:05.684196", "updated_at": "2022-07-28 11:04:05.684196"}}, {"pk": 293, "model": "campus.trashbin", "fields": {"token": "253CAN", "current_amount": 0, "total_amount": 10, "location_x": 3, "location_y": 0, "floor": 59, "created_at": "2022-07-28 11:04:05.684196", "updated_at": "2022-07-28 11:04:05.684196"}}, {"pk": 294, "model": "campus.trashbin", "fields": {"token": "253GLA", "current_amount": 0, "total_amount": 10, "location_x": 4, "location_y": 0, "floor": 59, "created_at": "2022-07-28 11:04:05.684196", "updated_at": "2022-07-28 11:04:05.684196"}}, {"pk": 295, "model": "campus.trashbin", "fields": {"token": "253PPR", "current_amount": 0, "total_amount": 10, "location_x": 5, "location_y": 0, "floor": 59, "created_at": "2022-07-28 11:04:05.684196", "updated_at": "2022-07-28 11:04:05.684196"}}, {"pk": 296, "model": "campus.trashbin", "fields": {"token": "254GER", "current_amount": 0, "total_amount": 10, "location_x": 1, "location_y": 0, "floor": 60, "created_at": "2022-07-28 11:04:05.684196", "updated_at": "2022-07-28 11:04:05.684196"}}, {"pk": 297, "model": "campus.trashbin", "fields": {"token": "254PET", "current_amount": 0, "total_amount": 10, "location_x": 2, "location_y": 0, "floor": 60, "created_at": "2022-07-28 11:04:05.684196", "updated_at": "2022-07-28 11:04:05.684196"}}, {"pk": 298, "model": "campus.trashbin", "fields": {"token": "254CAN", "current_amount": 0, "total_amount": 10, "location_x": 3, "location_y": 0, "floor": 60, "created_at": "2022-07-28 11:04:05.684196", "updated_at": "2022-07-28 11:04:05.684196"}}, {"pk": 299, "model": "campus.trashbin", "fields": {"token": "254GLA", "current_amount": 0, "total_amount": 10, "location_x": 4, "location_y": 0, "floor": 60, "created_at": "2022-07-28 11:04:05.684196", "updated_at": "2022-07-28 11:04:05.684196"}}, {"pk": 300, "model": "campus.trashbin", "fields": {"token": "254PPR", "current_amount": 0, "total_amount": 10, "location_x": 5, "location_y": 0, "floor": 60, "created_at": "2022-07-28 11:04:05.684196", "updated_at": "2022-07-28 11:04:05.684196"}}]